LICENSE
README.md
Viper.pth
Viper/__init__.py
Viper/__startup__.py
Viper/exceptions.py
Viper/format.py
Viper/frozendict.py
Viper/interactive.py
Viper/io.py
Viper/pickle_utils.py
Viper/warnings.py
Viper/abc/__init__.py
Viper/abc/connection.py
Viper/abc/io.py
Viper/abc/utils.py
Viper/collections/__init__.py
Viper/collections/isomorph.py
Viper/debugging/__init__.py
Viper/debugging/chrono.py
Viper/debugging/utils.py
Viper/meta/__init__.py
Viper/meta/decorators.py
Viper/meta/iterable.py
Viper/meta/procedural.py
Viper/meta/scope.py
Viper/meta/utils.py
viper_lib-1.5.2.dist-info/METADATA
viper_lib-1.5.2.dist-info/WHEEL
viper_lib-1.5.2.dist-info/licenses/LICENSE
viper_lib-1.5.2.dist-info/RECORD
