Metadata-Version: 2.1
Name: viper_lib
Version: 1.5.2
Summary: A Python library full of useful Python tools.
Project-URL: Repository, https://github.com/MrVoustache/Viper
Project-URL: Bug Tracker, https://github.com/MrVoustache/Viper/issues
Author-email: Vincent Raulin <vincent.raulin.n7@gmail.com>
License: MIT License
License-File: LICENSE
Classifier: License :: OSI Approved :: MIT License
Classifier: Operating System :: OS Independent
Classifier: Programming Language :: Python :: 3
Requires-Python: >=3.11
